abismal/VERSION
abismal/__init__.py
abismal/callbacks/__init__.py
abismal/callbacks/history.py
abismal/callbacks/mtz.py
abismal/callbacks/peak_finder.py
abismal/callbacks/phenix.py
abismal/callbacks/standardization_freezer.py
abismal/callbacks/weight_saver.py
abismal/command_line/__init__.py
abismal/command_line/abismal.py
abismal/command_line/cchalf.py
abismal/command_line/friedelize.py
abismal/command_line/plot_history.py
abismal/command_line/parser/__init__.py
abismal/command_line/parser/architecture.py
abismal/command_line/parser/custom_types.py
abismal/command_line/parser/io.py
abismal/command_line/parser/likelihood.py
abismal/command_line/parser/optimizer.py
abismal/command_line/parser/phenix.py
abismal/command_line/parser/priors.py
abismal/command_line/parser/ray.py
abismal/command_line/parser/surrogate_posterior.py
abismal/command_line/parser/tf.py
abismal/command_line/parser/training.py
abismal/distributions/__init__.py
abismal/distributions/folded_normal.py
abismal/distributions/nakagami.py
abismal/distributions/rice.py
abismal/distributions/rice_woolfson.py
abismal/distributions/truncated_normal.py
abismal/io/__init__.py
abismal/io/common.py
abismal/io/crystfel.py
abismal/io/dials.py
abismal/io/loader.py
abismal/io/manager.py
abismal/io/mtz.py
abismal/io/stream.py
abismal/io/tf_settings.py
abismal/io/utils.py
abismal/layers/__init__.py
abismal/layers/combinations.py
abismal/layers/feed_forward.py
abismal/layers/normalization.py
abismal/layers/positional_encoding.py
abismal/layers/standardization.py
abismal/likelihood/__init__.py
abismal/likelihood/laplace.py
abismal/likelihood/location_scale.py
abismal/likelihood/normal.py
abismal/likelihood/student.py
abismal/merging/__init__.py
abismal/merging/merging.py
abismal/optimizers/__init__.py
abismal/optimizers/adabelief.py
abismal/optimizers/adam.py
abismal/optimizers/base.py
abismal/optimizers/optimizer_dict.py
abismal/optimizers/wadam.py
abismal/prior/base.py
abismal/prior/normal.py
abismal-0.0.7.dist-info/licenses/LICENSE
abismal-0.0.7.dist-info/METADATA
abismal-0.0.7.dist-info/WHEEL
abismal-0.0.7.dist-info/entry_points.txt
abismal-0.0.7.dist-info/top_level.txt
abismal-0.0.7.dist-info/RECORD
