Metadata-Version: 2.4
Name: abismal
Version: 0.0.7
Summary: Stochastic merging for diffraction data.
Author-email: "Kevin M. Dalton" <kmdalton@slac.stanford.edu>
License: MIT
Project-URL: Repository, https://github.com/rs-station/abismal
Project-URL: Issues, https://github.com/rs-station/abismal/issues
Requires-Python: <3.13,>=3.9
License-File: LICENSE
Requires-Dist: reciprocalspaceship>=0.9.16
Requires-Dist: tqdm
Requires-Dist: tensorflow-probability[tf]==0.25
Requires-Dist: tensorflow==2.18.0
Requires-Dist: matplotlib
Requires-Dist: seaborn
Requires-Dist: rs-booster
Requires-Dist: ray
Provides-Extra: dev
Requires-Dist: pytest; extra == "dev"
Requires-Dist: pytest-cov; extra == "dev"
Requires-Dist: pytest-xdist; extra == "dev"
Provides-Extra: cuda
Requires-Dist: tensorflow[and-cuda]==2.18.0; extra == "cuda"
Dynamic: license-file
